LFLib/LFLib.py
LFLib/__init__.py
LFLib-0.3.1.dist-info/LICENSE
LFLib-0.3.1.dist-info/METADATA
LFLib-0.3.1.dist-info/WHEEL
LFLib-0.3.1.dist-info/top_level.txt
LFLib-0.3.1.dist-info/RECORD
