Metadata-Version: 2.1
Name: LFLib
Version: 0.3.1
Summary: This module provides a variety of quality of life functions.
Home-page: https://github.com/LukasFun/LFLib
Author: LukasFun
Author-email: lfreudenberg@uni-osnabrueck.de
Classifier: Programming Language :: Python :: 3
Classifier: License :: OSI Approved :: MIT License
Classifier: Operating System :: OS Independent
Requires-Python: >=3.6
License-File: LICENSE
